__init__.py
groupcast.py
groupcast-1.1.2.dist-info/licenses/LICENCE
groupcast-1.1.2.dist-info/METADATA
groupcast-1.1.2.dist-info/WHEEL
groupcast-1.1.2.dist-info/top_level.txt
groupcast-1.1.2.dist-info/RECORD
