Metadata-Version: 2.4
Name: groupcast
Version: 1.1.2
Summary: Dynamic method broadcasting to groups of objects
Author-email: Tzur Soffer <tzur.soffer@gmail.com>
License-Expression: MIT
Project-URL: Homepage, https://github.com/TzurSoffer/Groupcast
Project-URL: Repository, https://github.com/TzurSoffer/Groupcast
Keywords: delegation,broadcasting,group,OOP,metaprogramming
Classifier: Programming Language :: Python :: 3
Classifier: Operating System :: OS Independent
License-File: LICENCE
Dynamic: license-file
